MANIFEST.in
README.md
requirements.txt
setup.py
demo/__init__.py
demo/demo.py
keras_perturbation/__init__.py
keras_perturbation/constraint.py
keras_perturbation/perturbation.py
keras_perturbation.egg-info/PKG-INFO
keras_perturbation.egg-info/SOURCES.txt
keras_perturbation.egg-info/dependency_links.txt
keras_perturbation.egg-info/requires.txt
keras_perturbation.egg-info/top_level.txt
tests/__init__.py
tests/test_constraint.py
tests/test_perturbation.py